molgenis_emx2_pyclient/__init__.py
molgenis_emx2_pyclient/client.py
molgenis_emx2_pyclient/constants.py
molgenis_emx2_pyclient/exceptions.py
molgenis_emx2_pyclient/graphql_queries.py
molgenis_emx2_pyclient/metadata.py
molgenis_emx2_pyclient/utils.py
molgenis_emx2_pyclient-13.77.1.dist-info/licenses/LICENSE
molgenis_emx2_pyclient-13.77.1.dist-info/METADATA
molgenis_emx2_pyclient-13.77.1.dist-info/WHEEL
molgenis_emx2_pyclient-13.77.1.dist-info/top_level.txt
molgenis_emx2_pyclient-13.77.1.dist-info/RECORD
