Metadata-Version: 2.4
Name: molgenis-emx2-pyclient
Version: 13.77.1
Summary: Python client for the Molgenis EMX2 API
Classifier: Programming Language :: Python :: 3
Classifier: License :: OSI Approved :: GNU Lesser General Public License v3 (LGPLv3)
Classifier: Operating System :: OS Independent
Requires-Python: >=3.10
License-File: LICENSE
Requires-Dist: requests>=2.31.0
Requires-Dist: pandas>=2.2.2
Requires-Dist: pytest>=9.0.2
Requires-Dist: pytest-asyncio>=1.3.0
Requires-Dist: python-dotenv>=1.2.1
Requires-Dist: openpyxl>=3.1.5
Dynamic: license-file
